spex/__init__.py
spex/__main__.py
spex/parse.py
spex/progressbar.py
spex/py.typed
spex/validate.py
spex/writer.py
spex/xml.py
spex/htmlspec/__init__.py
spex/htmlspec/css.py
spex/htmlspec/htmlrenderer.py
spex/htmlspec/parser.py
spex/htmlspec/stream.py
spex/htmlspec/docx/__init__.py
spex/htmlspec/docx/document.py
spex/htmlspec/docx/docxutils.py
spex/htmlspec/docx/header.py
spex/htmlspec/docx/numbering.py
spex/htmlspec/docx/runproperties.py
spex/htmlspec/docx/styles.py
spex/htmlspec/docx/tablewrap.py
spex/htmlspec/docx/tags.py
spex/htmlspec/docx/types.py
spex/jsonspec/__init__.py
spex/jsonspec/defs.py
spex/jsonspec/document.py
spex/jsonspec/exceptions.py
spex/jsonspec/lint.py
spex/jsonspec/parse.py
spex/jsonspec/parserargs.py
spex/jsonspec/queries.py
spex/jsonspec/rowiter.py
spex/jsonspec/extractors/__init__.py
spex/jsonspec/extractors/figure.py
spex/jsonspec/extractors/helpers.py
spex/jsonspec/extractors/regular_expressions.py
spex/jsonspec/extractors/skiptable.py
spex/jsonspec/extractors/structtable.py
spex/jsonspec/extractors/valuetable.py
spex/jsonspec/quirks/__init__.py
spex/jsonspec/quirks/kv.py
spex/jsonspec/quirks/mi.py
spex/jsonspec/quirks/nvm.py
spex/jsonspec/quirks/zoned.py
spex/log/__init__.py
spex/log/_log_config.py
spex/resources/stage2.schema.json
spexsrv/__init__.py
spexsrv/__main__.py
spexsrv/py.typed
spexsrv/application/__init__.py
spexsrv/application/app.py
spexsrv/application/report_view.py
spexsrv/static/alpinejs.3.13.5.js
spexsrv/static/bulma-0.9.4.min.css
spexsrv/static/fontawesome.6.5.1.min.css
spexsrv/templates/base.html
spexsrv/templates/report.html
spexsrv/templates/upload-form.html
nvme_spex-0.7.dist-info/METADATA
nvme_spex-0.7.dist-info/WHEEL
nvme_spex-0.7.dist-info/entry_points.txt
nvme_spex-0.7.dist-info/top_level.txt
nvme_spex-0.7.dist-info/RECORD
