Metadata-Version: 2.1
Name: nvme-spex
Version: 0.7
Summary: extract data structures from docx/HTML specification
Author-email: Jesper Wendel Devantier <j.devantier@samsung.com>
Maintainer-email: Jesper Wendel Devantier <j.devantier@samsung.com>
License: MIT
Requires-Python: >=3.11
Requires-Dist: lxml <5.0,>=4.9.2
Requires-Dist: loguru <0.8,>=0.6
Requires-Dist: jsonschema >=4.21.1
Requires-Dist: gcgen
Requires-Dist: types-jsonschema
Requires-Dist: quart
Provides-Extra: dev
Requires-Dist: build ; extra == 'dev'
Requires-Dist: pytest ; extra == 'dev'
Requires-Dist: mypy ; extra == 'dev'
Requires-Dist: black ; extra == 'dev'
Requires-Dist: types-lxml ; extra == 'dev'
Requires-Dist: types-jsonschema ; extra == 'dev'
Requires-Dist: isort ; extra == 'dev'
Requires-Dist: flake8 ; extra == 'dev'
Requires-Dist: Flake8-pyproject ; extra == 'dev'
Requires-Dist: sphinx ; extra == 'dev'
Requires-Dist: sphinx-copybutton ; extra == 'dev'
Requires-Dist: furo ; extra == 'dev'
Requires-Dist: wheel ; extra == 'dev'
Requires-Dist: twine ; extra == 'dev'
Requires-Dist: types-setuptools ; extra == 'dev'
Requires-Dist: reuse ; extra == 'dev'
